LICENSE.txt
MANIFEST.in
README.rst
setup.cfg
setup.py
Wordbatch.egg-info/PKG-INFO
Wordbatch.egg-info/SOURCES.txt
Wordbatch.egg-info/dependency_links.txt
Wordbatch.egg-info/requires.txt
Wordbatch.egg-info/top_level.txt
data/Tweets.csv
scripts/backends_benchmark.py
scripts/classify_airline_sentiment.py
scripts/wordbag_regressor.py
scripts/wordhash_regressor.py
scripts/wordseq_regressor.py
scripts/wordvec_regressor.py
wordbatch/__init__.py
wordbatch/batcher.py
wordbatch/batcher_bu1.py
wordbatch/data_utils.py
wordbatch/extractors/MurmurHash3.cpp
wordbatch/extractors/MurmurHash3.h
wordbatch/extractors/__init__.py
wordbatch/extractors/extractors.pyx
wordbatch/models/__init__.py
wordbatch/models/avx_ext.c
wordbatch/models/avx_ext.h
wordbatch/models/fm_ftrl.pyx
wordbatch/models/ftrl.pyx
wordbatch/models/ftrl32.pyx
wordbatch/models/nn_relu_h1.pyx
wordbatch/models/nn_relu_h2.pyx
wordbatch/pipelines/__init__.py
wordbatch/pipelines/apply.py
wordbatch/pipelines/apply_batch.py
wordbatch/pipelines/apply_groupby.py
wordbatch/pipelines/batch_transformer.py
wordbatch/pipelines/feature_union.py
wordbatch/pipelines/wordbatch.py
wordbatch/transformers/__init__.py
wordbatch/transformers/dictionary.py
wordbatch/transformers/pandas_pick.py
wordbatch/transformers/text_normalizer.py
wordbatch/transformers/tokenizer.py