Metadata-Version: 2.1
Name: Wordbatch
Version: 1.4.8
Summary: Python library for distributed AI processing pipelines, using swappable scheduler backends
Home-page: https://github.com/anttttti/Wordbatch
Author: Antti Puurula
Author-email: antti.puurula@yahoo.com
License: GNU GPL 2.0
Platform: UNKNOWN
Classifier: Development Status :: 4 - Beta
Classifier: Intended Audience :: Developers
Classifier: License :: OSI Approved :: GNU General Public License v2 (GPLv2)
Classifier: Programming Language :: Python :: 3.6
Classifier: Programming Language :: Python :: 3.7
Classifier: Programming Language :: Python :: 3.8
Classifier: Programming Language :: Cython
Classifier: Topic :: Scientific/Engineering :: Artificial Intelligence
Classifier: Topic :: Software Development :: Libraries :: Python Modules
Provides-Extra: dev
